README.md
setup.py
webreq/__init__.py
webreq/__version__.py
webreq/_internal_utils.py
webreq/adapters.py
webreq/api.py
webreq/auth.py
webreq/certs.py
webreq/compat.py
webreq/cookies.py
webreq/exceptions.py
webreq/help.py
webreq/hooks.py
webreq/models.py
webreq/packages.py
webreq/sessions.py
webreq/status_codes.py
webreq/structures.py
webreq/utils.py
webreq.egg-info/PKG-INFO
webreq.egg-info/SOURCES.txt
webreq.egg-info/dependency_links.txt
webreq.egg-info/requires.txt
webreq.egg-info/top_level.txt