Metadata-Version: 1.0
Name: webreq
Version: 1.0.2
Summary: Web request module
Home-page: UNKNOWN
Author: mulva
Author-email: UNKNOWN
License: UNKNOWN
Platform: UNKNOWN
